docs/_downloads/066a96b3e7333f9a789eb7e687c45875/plot_histogram_2d.py
docs/_downloads/09f048ba9debdfb740a9a828a370954b/plot_inference_1d_resolve.py
docs/_downloads/29d06c7b2b9a8473c8472010e9733584/plot_inference_1d_skytem.py
docs/_downloads/2b313676e6ab4e7fef5cb85211b43803/plot_model_3d.py
docs/_downloads/2dd62cc642303de6b0d2af1a789eccaa/plot_skytem_datapoint.py
docs/_downloads/3bf606a1e1bcade69bb1094393e978cd/plot_histogram_3d.py
docs/_downloads/3c5056a53b95767fadaa921bc11aca48/plot_Distributions.py
docs/_downloads/439c06574d36795305525eb492c7861b/plot_tempest_datapoint.py
docs/_downloads/464247fcfe95c715a98148433d5ae85a/inference_2d_plotting.py
docs/_downloads/48c7722b252e7ddf33d95322115dcaf5/plot_rectilinear_mesh_2d.py
docs/_downloads/48f0be9987c0cd931b23ce187c305d56/plot_inference_2d_resolve.py
docs/_downloads/53dc65a717762d4693b891c0caabbde0/plot_StatArray.py
docs/_downloads/54ce350904e65ae0e6717397118ed43f/plot_inference_2d_tempest.py
docs/_downloads/553c44c8f0a927032d89154ad011db0e/plot_rectilinear_mesh_1d.py
docs/_downloads/5b5d77f6a7b150a24e5d195babd5a68d/plot_DataArray.py
docs/_downloads/5fec87f3cbcb4a4b1c15391a27334984/plot_inference_1d_tempest.py
docs/_downloads/6c96ba056672a7e415f479abafdaf81d/plot_pointcloud3d.py
docs/_downloads/762d4f393eb8c7294ca843748ae360e3/plot_skytem_dataset.py
docs/_downloads/76ee0e4ad4daaf5556108538842b1772/hdf5.py
docs/_downloads/7f3bb43ebb9eba21697953fbfc04f6d2/plot_rectilinear_mesh_3d.py
docs/_downloads/83471875085bd5964f72b6b955c92f62/test.py
docs/_downloads/8a8596f0390404145eca225a8f310218/plot_frequency_dataset.py
docs/_downloads/950360871c2acdf8ad1b1627e54009da/plot_resolve_datapoint.py
docs/_downloads/9570534d71f4f6a00b8f20360000c3ff/plot_histogram_1d.py
docs/_downloads/a209de4dae1a6f3f3daeab70fe6f557a/plot_inference_1d_skytem.py
docs/_downloads/b65392b576618a906ad35b58f026489b/plot_model_2d.py
docs/_downloads/c50f5c5fdb1ab3a85236c34d440144a2/plot_inference_1d_resolve.py
geobipy-2.3.2.dist-info/licenses/LICENSE-BSD.md
geobipy-2.3.2.dist-info/licenses/LICENSE-GPLv2.md
geobipy-2.3.2.dist-info/licenses/LICENSE.md
geobipy-2.3.2.dist-info/METADATA
geobipy-2.3.2.dist-info/WHEEL
geobipy-2.3.2.dist-info/entry_points.txt
geobipy-2.3.2.dist-info/top_level.txt
geobipy-2.3.2.dist-info/RECORD
