Metadata-Version: 2.4
Name: geobipy
Version: 2.3.2
Summary: McMC inversion of airborne electromagnetic data
Author-email: Leon Foks <nfoks@contractor.usgs.gov>, Burke Minsley <bminsley@usgs.gov>
Keywords: inversion,bayesian
Classifier: License :: OSI Approved
Classifier: License :: CC0 1.0 Universal (CC0 1.0) Public Domain Dedication
Classifier: License :: OSI Approved :: GNU General Public License v2 (GPLv2)
Classifier: License :: OSI Approved :: BSD License
Classifier: Programming Language :: Python :: 3
Classifier: Topic :: Scientific/Engineering
Requires-Python: >=3.10
License-File: LICENSE-BSD.md
License-File: LICENSE-GPLv2.md
License-File: LICENSE.md
Requires-Dist: numpy
Requires-Dist: scipy>=1.15.3
Requires-Dist: h5py
Requires-Dist: numba
Requires-Dist: pandas
Requires-Dist: netcdf4
Requires-Dist: matplotlib
Requires-Dist: pyvista
Requires-Dist: progressbar2
Requires-Dist: cached-property
Requires-Dist: scikit-learn
Requires-Dist: pygmt
Requires-Dist: numba_kdtree
Requires-Dist: lmfit
Requires-Dist: mpi4py_utilities
Provides-Extra: docs
Requires-Dist: sphinx_gallery; extra == "docs"
Requires-Dist: sphinx_rtd_theme; extra == "docs"
Dynamic: license-file
